vegehub/__init__.py
vegehub/helpers.py
vegehub/vegehub.py
vegehub-0.1.26.dist-info/LICENSE.txt
vegehub-0.1.26.dist-info/METADATA
vegehub-0.1.26.dist-info/WHEEL
vegehub-0.1.26.dist-info/RECORD
