Metadata-Version: 2.3
Name: vegehub
Version: 0.1.26
Summary: A basic package for simplifying interactions with the Vegetronix VegeHub
License: GPL-3.0-or-later
Author: GhoweVege
Author-email: 85890024+GhoweVege@users.noreply.github.com
Requires-Python: >=3.12,<4.0
Classifier: License :: OSI Approved :: GNU General Public License v3 or later (GPLv3+)
Classifier: Programming Language :: Python :: 3
Classifier: Programming Language :: Python :: 3.12
Classifier: Programming Language :: Python :: 3.13
Requires-Dist: aiohttp (>=3.10.8,<4.0.0)
Project-URL: Homepage, https://www.vegetronix.com/Products/VG-HUB-RELAY/
Project-URL: Repository, https://github.com/GhoweVege/VegeHubPyPiLib
